la_businesses/.git/objects/08/0f34a407598181e9783debd40efee85ca37d4c
la_businesses/.git/objects/4b/825dc642cb6eb9a060e54bf8d69288fbee4904
la_businesses/.git/objects/58/1c55e609633b3214f495b6a7f4a92a8f01908e
la_businesses/.git/objects/b5/68c545e552ffae1d960931ecd2d28c13f23cd9
la_businesses/.git/objects/d8/ef049d6e7889551f31817553b1835cfd09cf86
la_businesses/__init__.py
la_businesses/la_businesses.py
la_businesses-0.1.1.dist-info/entry_points.txt
la_businesses-0.1.1.dist-info/WHEEL
la_businesses-0.1.1.dist-info/METADATA
la_businesses-0.1.1.dist-info/RECORD
