Metadata-Version: 2.1
Name: la-businesses
Version: 0.1.1
Summary: Save the latest database of businesses in Los Angeles as CSV and KML.
Home-page: UNKNOWN
License: MIT
Author: Manuel Ochoa
Author-email: dev@manuelochoa.com
Requires-Python: >=3.7,<4.0
Classifier: License :: OSI Approved :: MIT License
Classifier: Programming Language :: Python :: 3
Classifier: Programming Language :: Python :: 3.7
Requires-Dist: pandas (>=0.24.2,<0.25.0)
Requires-Dist: pytz (>=2018.9,<2019.0)
Requires-Dist: requests (>=2.21,<3.0)
Requires-Dist: simplekml (>=1.3,<2.0)
